maptekomf/maptek/__init__.py
maptekomf/maptek/__main__.py
maptekomf/maptek/cli.py
maptekomf/maptek/exporter.py
maptekomf/maptek/importer.py
maptekomf/maptek/workflow.py
maptekomf_maptek-1.0.4.dist-info/METADATA
maptekomf_maptek-1.0.4.dist-info/WHEEL
maptekomf_maptek-1.0.4.dist-info/top_level.txt
maptekomf_maptek-1.0.4.dist-info/RECORD
