Metadata-Version: 2.1
Name: maptekomf-maptek
Version: 1.0.4
Summary: Provides interoperability between Maptek SDK and OMF.
Author-email: Maptek <support@maptek.com.au>
License: Maptek End User Licence Agreement
Project-URL: Homepage, https://www.maptek.com
Project-URL: Documentation, https://help.maptek.com/mapteksdk/
Project-URL: Support, https://www.maptek.com/support/index.html
Keywords: mining,data,interchange
Classifier: Development Status :: 4 - Beta
Classifier: Operating System :: Microsoft :: Windows
Classifier: License :: Other/Proprietary License
Classifier: Programming Language :: Python :: 3.7
Classifier: Programming Language :: Python :: 3.8
Classifier: Programming Language :: Python :: 3.9
Classifier: Programming Language :: Python :: 3.10
Classifier: Programming Language :: Python :: 3.11
Classifier: Natural Language :: English
Classifier: Topic :: Scientific/Engineering
Classifier: Topic :: Scientific/Engineering :: Visualization
Requires-Python: <3.13,>=3.7
Requires-Dist: mapteksdk (<2.0.0,>=1.2.0)
Requires-Dist: pillow (<10.1.0,>=7.0.0)
Requires-Dist: omf (==1.0.1)
